mllp_http_https/__init__.py
mllp_http_https/http2mllp.py
mllp_http_https/https2mllp.py
mllp_http_https/log2file.py
mllp_http_https/main.py
mllp_http_https/mllp.py
mllp_http_https/mllp2http.py
mllp_http_https/mllp2https.py
mllp_http_https/net.py
mllp_http_https/version.py
mllp_https-1.2.41.dist-info/LICENSE.txt
mllp_https-1.2.41.dist-info/METADATA
mllp_https-1.2.41.dist-info/WHEEL
mllp_https-1.2.41.dist-info/entry_points.txt
mllp_https-1.2.41.dist-info/top_level.txt
mllp_https-1.2.41.dist-info/RECORD
