Metadata-Version: 2.1
Name: mllp-https
Version: 1.2.41
Summary: Translate between MLLP and HTTP/HTTPS
Home-page: https://github.com/tiagoepr/mllp-https
Author: Tiago Rodrigues/SECTRA Iberia
Author-email: Tiago.Rodrigues@sectra.com
License: MIT
Project-URL: Issues, https://github.com/tiagoepr/mllp-https/issues
Project-URL: Original Project by Rivet Health, https://github.com/rivethealth/mllp-http/
Classifier: License :: OSI Approved :: MIT License
Classifier: Operating System :: OS Independent
Classifier: Programming Language :: Python
Classifier: Programming Language :: Python :: 3
License-File: LICENSE.txt
Requires-Dist: requests
